INSTALL.txt
LICENSE.txt
MANIFEST.in
README.rst
setup.cfg
setup.py
doc/Makefile
doc/gh-pages.py
doc/gitwash_dumper.py
doc/make_examples_rst.py
doc/make_gallery.py
doc/requirements.txt
doc/rst_templates/autosummary/base.rst
doc/rst_templates/autosummary/class.rst
doc/rst_templates/autosummary/function.rst
doc/rst_templates/autosummary/module.rst
doc/source/bibliography.rst
doc/source/conf.py
doc/source/download.rst
doc/source/index.rst
doc/source/install.rst
doc/source/overview.rst
doc/source/test.rst
doc/source/developer/index.rst
doc/source/developer/gitwash/branch_dropdown.png
doc/source/developer/gitwash/configure_git.rst
doc/source/developer/gitwash/development_workflow.rst
doc/source/developer/gitwash/following_latest.rst
doc/source/developer/gitwash/forking_button.png
doc/source/developer/gitwash/forking_hell.rst
doc/source/developer/gitwash/git_development.rst
doc/source/developer/gitwash/git_install.rst
doc/source/developer/gitwash/git_intro.rst
doc/source/developer/gitwash/git_links.inc
doc/source/developer/gitwash/git_resources.rst
doc/source/developer/gitwash/index.rst
doc/source/developer/gitwash/known_projects.inc
doc/source/developer/gitwash/links.inc
doc/source/developer/gitwash/maintainer_workflow.rst
doc/source/developer/gitwash/patching.rst
doc/source/developer/gitwash/pull_button.png
doc/source/developer/gitwash/set_up_fork.rst
doc/source/developer/gitwash/this_project.inc
doc/source/reference/algorithms.approximation.rst
doc/source/reference/algorithms.assortativity.rst
doc/source/reference/algorithms.bipartite.rst
doc/source/reference/algorithms.block.rst
doc/source/reference/algorithms.boundary.rst
doc/source/reference/algorithms.centrality.rst
doc/source/reference/algorithms.chordal.rst
doc/source/reference/algorithms.clique.rst
doc/source/reference/algorithms.clustering.rst
doc/source/reference/algorithms.coloring.rst
doc/source/reference/algorithms.community.rst
doc/source/reference/algorithms.component.rst
dorthrithil_networkx.egg-info/PKG-INFO
dorthrithil_networkx.egg-info/SOURCES.txt
dorthrithil_networkx.egg-info/dependency_links.txt
dorthrithil_networkx.egg-info/not-zip-safe
dorthrithil_networkx.egg-info/requires.txt
dorthrithil_networkx.egg-info/top_level.txt
